webviz/__init__.py
webviz-0.0.1.dist-info/METADATA
webviz-0.0.1.dist-info/WHEEL
webviz-0.0.1.dist-info/top_level.txt
webviz-0.0.1.dist-info/RECORD
