Metadata-Version: 2.1
Name: webviz
Version: 0.0.1
Summary: Webviz is a static site generator that facilitates automatic reporting and visualization.
Home-page: https://github.com/Statoil/webviz
Author: Equinor ASA
Author-email: fg_gpl@equinor.com
License: UNKNOWN
Project-URL: Documentation, https://webviz.readthedocs.io
Project-URL: Bug Reports, https://github.com/Statoil/webviz/issues
Platform: UNKNOWN
Classifier: Programming Language :: Python :: 2
Classifier: Programming Language :: Python :: 3
Classifier: License :: OSI Approved :: GNU Lesser General Public License v3 or later (LGPLv3+)
Classifier: Operating System :: OS Independent
